cmos_noise_map/get_rts.py
cmos_noise_map/main.py
cmos_noise_map/map_maker.py
cmos_noise_map/tests/make_test_data.py
cmos_noise_map/tests/test_data.npy
cmos_noise_map/tests/test_get_rts.py
cmos_noise_map/utils/data_utils.py
cmos_noise_map/utils/get_rts_playground.py
cmos_noise_map/utils/read_write_utils.py
cmos_noise_map-0.1.4.dist-info/LICENSE.md
cmos_noise_map-0.1.4.dist-info/METADATA
cmos_noise_map-0.1.4.dist-info/WHEEL
cmos_noise_map-0.1.4.dist-info/entry_points.txt
cmos_noise_map-0.1.4.dist-info/RECORD
