Metadata-Version: 2.1
Name: cmos-noise-map
Version: 0.1.4
Summary: A tool to create a read noise map for CMOS detectors by modelling Random Telegraph Signal. This was originally created for use by LCOGT's BANZAI pipeline.
Author: Prerana Kottapalli
Requires-Python: >=3.8,<3.12
Classifier: Programming Language :: Python :: 3
Classifier: Programming Language :: Python :: 3.8
Classifier: Programming Language :: Python :: 3.9
Classifier: Programming Language :: Python :: 3.10
Classifier: Programming Language :: Python :: 3.11
Provides-Extra: docs
Requires-Dist: astropy (>=5.2.1,<6.0.0)
Requires-Dist: click (>=8.1.3,<9.0.0)
Requires-Dist: glob2 (>=0.7,<0.8)
Requires-Dist: ipython (>=8.9.0,<9.0.0)
Requires-Dist: matplotlib (>=3.6.3,<4.0.0)
Requires-Dist: myst-parser (>=0.18.1,<0.19.0)
Requires-Dist: nbsphinx (>=0.8.12,<0.9.0)
Requires-Dist: numpy (>=1.24.1,<2.0.0)
Requires-Dist: pandas (>=1.5.3,<2.0.0)
Requires-Dist: pandoc (>=2.3,<3.0)
Requires-Dist: pytest (>=7.2.1,<8.0.0)
Requires-Dist: scikit-learn (>=1.2.1,<2.0.0)
Requires-Dist: scipy (>=1.10.0,<2.0.0)
Requires-Dist: sphinx (>=4,<6) ; extra == "docs"
